AUTHORS
LICENSE
MANIFEST.in
README
README.md
setup.py
zombie_translator/__init__.py
zombie_translator.egg-info/PKG-INFO
zombie_translator.egg-info/SOURCES.txt
zombie_translator.egg-info/dependency_links.txt
zombie_translator.egg-info/not-zip-safe
zombie_translator.egg-info/top_level.txt