Metadata-Version: 1.0
Name: zombie-translator
Version: 0.1.1
Summary: The best way to understand and be understood by your zombie friends
Home-page: https://github.com/wieden-kennedy/zombie-translator
Author: Steven Skoczen
Author-email: steven.skoczen@wk.com
License: UNKNOWN
Platform: UNKNOWN
Classifier: Programming Language :: Python
Classifier: License :: OSI Approved :: BSD License
Classifier: Operating System :: OS Independent
Classifier: Development Status :: 4 - Beta
Classifier: Environment :: Web Environment
Classifier: Intended Audience :: Developers
Classifier: Topic :: Software Development :: Libraries :: Python Modules
